{
  "name": "英语",
  "type": "show",
  "id": "23b8d90e014395e08cde15d52910bf4b9f30ec66",
  "res": [
    {
      "name": "语音",
      "no": "001",
      "type": "video",
      "url": "http://rspcourse.chinaedu.net/00700/499193_20180827_2/9E835990A7C24E72BD287AEBF4A1F152/res/3course!!%e8%a7%86%e9%a2%91%e8%ae%b2%e8%a7%a3/001%e8%af%ad%e9%9f%b3/%e5%88%87%e7%89%87/001%e8%af%ad%e9%9f%b3/video.m3u8"
    },
    {
      "name": "名词",
      "no": "002",
      "type": "video",
      "url": "http://rspcourse.chinaedu.net/00700/499193_20180827_2/9E835990A7C24E72BD287AEBF4A1F152/res/3course!!%e8%a7%86%e9%a2%91%e8%ae%b2%e8%a7%a3/002%e5%90%8d%e8%af%8d/%e5%88%87%e7%89%87/002%e5%90%8d%e8%af%8d/video.m3u8"
    },
    {
      "name": "代词",
      "no": "003",
      "type": "video",
      "url": "http://rspcourse.chinaedu.net/00700/499193_20180827_2/9E835990A7C24E72BD287AEBF4A1F152/res/3course!!%e8%a7%86%e9%a2%91%e8%ae%b2%e8%a7%a3/003%e4%bb%a3%e8%af%8d/%e5%88%87%e7%89%87/003%e4%bb%a3%e8%af%8d/video.m3u8"
    },
    {
      "name": "动词",
      "no": "004",
      "type": "video",
      "url": "http://rspcourse.chinaedu.net/00700/499193_20180827_2/9E835990A7C24E72BD287AEBF4A1F152/res/3course!!%e8%a7%86%e9%a2%91%e8%ae%b2%e8%a7%a3/004%e5%8a%a8%e8%af%8d/%e5%88%87%e7%89%87/004%e5%8a%a8%e8%af%8d/video.m3u8"
    },
    {
      "name": "冠词",
      "no": "005",
      "type": "video",
      "url": "http://rspcourse.chinaedu.net/00700/499193_20180827_2/9E835990A7C24E72BD287AEBF4A1F152/res/3course!!%e8%a7%86%e9%a2%91%e8%ae%b2%e8%a7%a3/005%e5%86%a0%e8%af%8d/%e5%88%87%e7%89%87/005%e5%86%a0%e8%af%8d/video.m3u8"
    },
    {
      "name": "连词",
      "no": "006",
      "type": "video",
      "url": "http://rspcourse.chinaedu.net/00700/499193_20180827_2/9E835990A7C24E72BD287AEBF4A1F152/res/3course!!%e8%a7%86%e9%a2%91%e8%ae%b2%e8%a7%a3/006%e8%bf%9e%e8%af%8d/%e5%88%87%e7%89%87/006%e8%bf%9e%e8%af%8d/video.m3u8"
    },
    {
      "name": "数词",
      "no": "007",
      "type": "video",
      "url": "http://rspcourse.chinaedu.net/00700/499193_20180827_2/9E835990A7C24E72BD287AEBF4A1F152/res/3course!!%e8%a7%86%e9%a2%91%e8%ae%b2%e8%a7%a3/007%e6%95%b0%e8%af%8d/%e5%88%87%e7%89%87/007%e6%95%b0%e8%af%8d/video.m3u8"
    },
    {
      "name": "介词",
      "no": "008",
      "type": "video",
      "url": "http://rspcourse.chinaedu.net/00700/499193_20180827_2/9E835990A7C24E72BD287AEBF4A1F152/res/3course!!%e8%a7%86%e9%a2%91%e8%ae%b2%e8%a7%a3/008%e4%bb%8b%e8%af%8d/%e5%88%87%e7%89%87/008%e4%bb%8b%e8%af%8d/video.m3u8"
    },
    {
      "name": "基本概念",
      "no": "009",
      "type": "video",
      "url": "http://rspcourse.chinaedu.net/00700/499193_20180827_2/9E835990A7C24E72BD287AEBF4A1F152/res/3course!!%e8%a7%86%e9%a2%91%e8%ae%b2%e8%a7%a3/009%e5%9f%ba%e6%9c%ac%e6%a6%82%e5%bf%b5/%e5%88%87%e7%89%87/009%e5%9f%ba%e6%9c%ac%e6%a6%82%e5%bf%b5/video.m3u8"
    },
    {
      "name": "时态",
      "no": "010",
      "type": "video",
      "url": "http://rspcourse.chinaedu.net/00700/499193_20180827_2/9E835990A7C24E72BD287AEBF4A1F152/res/3course!!%e8%a7%86%e9%a2%91%e8%ae%b2%e8%a7%a3/010%e6%97%b6%e6%80%81/%e5%88%87%e7%89%87/010%e6%97%b6%e6%80%81/video.m3u8"
    },
    {
      "name": "语态",
      "no": "011",
      "type": "video",
      "url": "http://rspcourse.chinaedu.net/00700/499193_20180827_2/9E835990A7C24E72BD287AEBF4A1F152/res/3course!!%e8%a7%86%e9%a2%91%e8%ae%b2%e8%a7%a3/011%e8%af%ad%e6%80%81/%e5%88%87%e7%89%87/011%e8%af%ad%e6%80%81/video.m3u8"
    },
    {
      "name": "不定式",
      "no": "012",
      "type": "video",
      "url": "http://rspcourse.chinaedu.net/00700/499193_20180827_2/9E835990A7C24E72BD287AEBF4A1F152/res/3course!!%e8%a7%86%e9%a2%91%e8%ae%b2%e8%a7%a3/012%e4%b8%8d%e5%ae%9a%e5%bc%8f/%e5%88%87%e7%89%87/012%e4%b8%8d%e5%ae%9a%e5%bc%8f/video.m3u8"
    },
    {
      "name": "动名词",
      "no": "013",
      "type": "video",
      "url": "http://rspcourse.chinaedu.net/00700/499193_20180827_2/9E835990A7C24E72BD287AEBF4A1F152/res/3course!!%e8%a7%86%e9%a2%91%e8%ae%b2%e8%a7%a3/013%e5%8a%a8%e5%90%8d%e8%af%8d/%e5%88%87%e7%89%87/013%e5%8a%a8%e5%90%8d%e8%af%8d/video.m3u8"
    },
    {
      "name": "分词",
      "no": "014",
      "type": "video",
      "url": "http://rspcourse.chinaedu.net/00700/499193_20180827_2/9E835990A7C24E72BD287AEBF4A1F152/res/3course!!%e8%a7%86%e9%a2%91%e8%ae%b2%e8%a7%a3/014%e5%88%86%e8%af%8d/%e5%88%87%e7%89%87/014%e5%88%86%e8%af%8d/video.m3u8"
    },
    {
      "name": "名词性从句",
      "no": "015",
      "type": "video",
      "url": "http://rspcourse.chinaedu.net/00700/499193_20180827_2/9E835990A7C24E72BD287AEBF4A1F152/res/3course!!%e8%a7%86%e9%a2%91%e8%ae%b2%e8%a7%a3/015%e5%90%8d%e8%af%8d%e6%80%a7%e4%bb%8e%e5%8f%a5/%e5%88%87%e7%89%87/015%e5%90%8d%e8%af%8d%e6%80%a7%e4%bb%8e%e5%8f%a5/video.m3u8"
    },
    {
      "name": "定语从句",
      "no": "016",
      "type": "video",
      "url": "http://rspcourse.chinaedu.net/00700/499193_20180827_2/9E835990A7C24E72BD287AEBF4A1F152/res/3course!!%e8%a7%86%e9%a2%91%e8%ae%b2%e8%a7%a3/016%e5%ae%9a%e8%af%ad%e4%bb%8e%e5%8f%a5/%e5%88%87%e7%89%87/016%e5%ae%9a%e8%af%ad%e4%bb%8e%e5%8f%a5/video.m3u8"
    },
    {
      "name": "状语从句",
      "no": "017",
      "type": "video",
      "url": "http://rspcourse.chinaedu.net/00700/499193_20180827_2/9E835990A7C24E72BD287AEBF4A1F152/res/3course!!%e8%a7%86%e9%a2%91%e8%ae%b2%e8%a7%a3/017%e7%8a%b6%e8%af%ad%e4%bb%8e%e5%8f%a5/%e5%88%87%e7%89%87/017%e7%8a%b6%e8%af%ad%e4%bb%8e%e5%8f%a5/video.m3u8"
    },
    {
      "name": "倒装句",
      "no": "018",
      "type": "video",
      "url": "http://rspcourse.chinaedu.net/00700/499193_20180827_2/9E835990A7C24E72BD287AEBF4A1F152/res/3course!!%e8%a7%86%e9%a2%91%e8%ae%b2%e8%a7%a3/018%e5%80%92%e8%a3%85%e5%8f%a5/%e5%88%87%e7%89%87/018%e5%80%92%e8%a3%85%e5%8f%a5/video.m3u8"
    },
    {
      "name": "主谓一致",
      "no": "019",
      "type": "video",
      "url": "http://rspcourse.chinaedu.net/00700/499193_20180827_2/9E835990A7C24E72BD287AEBF4A1F152/res/3course!!%e8%a7%86%e9%a2%91%e8%ae%b2%e8%a7%a3/019%e4%b8%bb%e8%b0%93%e4%b8%80%e8%87%b4/%e5%88%87%e7%89%87/019%e4%b8%bb%e8%b0%93%e4%b8%80%e8%87%b4/video.m3u8"
    },
    {
      "name": "形容词副词的比较级与最高级",
      "no": "020",
      "type": "video",
      "url": "http://rspcourse.chinaedu.net/00700/499193_20180827_2/9E835990A7C24E72BD287AEBF4A1F152/res/3course!!%e8%a7%86%e9%a2%91%e8%ae%b2%e8%a7%a3/020%e5%bd%a2%e5%ae%b9%e8%af%8d%e5%89%af%e8%af%8d%e7%9a%84%e6%af%94%e8%be%83%e7%ba%a7%e4%b8%8e%e6%9c%80%e9%ab%98%e7%ba%a7/%e5%88%87%e7%89%87/020%e5%bd%a2%e5%ae%b9%e8%af%8d%e5%89%af%e8%af%8d%e7%9a%84%e6%af%94%e8%be%83%e7%ba%a7%e4%b8%8e%e6%9c%80%e9%ab%98%e7%ba%a7/video.m3u8"
    },
    {
      "name": "虚拟语气",
      "no": "021",
      "type": "video",
      "url": "http://rspcourse.chinaedu.net/00700/499193_20180827_2/9E835990A7C24E72BD287AEBF4A1F152/res/3course!!%e8%a7%86%e9%a2%91%e8%ae%b2%e8%a7%a3/021%e8%99%9a%e6%8b%9f%e8%af%ad%e6%b0%94/%e5%88%87%e7%89%87/021%e8%99%9a%e6%8b%9f%e8%af%ad%e6%b0%94/video.m3u8"
    },
    {
      "name": "语音",
      "no": "022",
      "type": "video",
      "url": "http://rspcourse.chinaedu.net/00700/499193_20180827_2/9E835990A7C24E72BD287AEBF4A1F152/res/3course!!%e8%a7%86%e9%a2%91%e8%ae%b2%e8%a7%a3/022%e8%af%ad%e9%9f%b3/%e5%88%87%e7%89%87/022%e8%af%ad%e9%9f%b3/video.m3u8"
    },
    {
      "name": "词汇与语法",
      "no": "023",
      "type": "video",
      "url": "http://rspcourse.chinaedu.net/00700/499193_20180827_2/9E835990A7C24E72BD287AEBF4A1F152/res/3course!!%e8%a7%86%e9%a2%91%e8%ae%b2%e8%a7%a3/023%e8%af%8d%e6%b1%87%e4%b8%8e%e8%af%ad%e6%b3%95/%e5%88%87%e7%89%87/023%e8%af%8d%e6%b1%87%e4%b8%8e%e8%af%ad%e6%b3%95/video.m3u8"
    },
    {
      "name": "完形填空",
      "no": "024",
      "type": "video",
      "url": "http://rspcourse.chinaedu.net/00700/499193_20180827_2/9E835990A7C24E72BD287AEBF4A1F152/res/3course!!%e8%a7%86%e9%a2%91%e8%ae%b2%e8%a7%a3/024%e5%ae%8c%e5%bd%a2%e5%a1%ab%e7%a9%ba/%e5%88%87%e7%89%87/024%e5%ae%8c%e5%bd%a2%e5%a1%ab%e7%a9%ba/video.m3u8"
    },
    {
      "name": "阅读理解",
      "no": "025",
      "type": "video",
      "url": "http://rspcourse.chinaedu.net/00700/499193_20180827_2/9E835990A7C24E72BD287AEBF4A1F152/res/3course!!%e8%a7%86%e9%a2%91%e8%ae%b2%e8%a7%a3/025%e9%98%85%e8%af%bb%e7%90%86%e8%a7%a3/%e5%88%87%e7%89%87/025%e9%98%85%e8%af%bb%e7%90%86%e8%a7%a3/video.m3u8"
    },
    {
      "name": "补全对话",
      "no": "026",
      "type": "video",
      "url": "http://rspcourse.chinaedu.net/00700/499193_20180827_2/9E835990A7C24E72BD287AEBF4A1F152/res/3course!!%e8%a7%86%e9%a2%91%e8%ae%b2%e8%a7%a3/026%e8%a1%a5%e5%85%a8%e5%af%b9%e8%af%9d/%e5%88%87%e7%89%87/026%e8%a1%a5%e5%85%a8%e5%af%b9%e8%af%9d/video.m3u8"
    },
    {
      "name": "书面表达",
      "no": "027",
      "type": "video",
      "url": "http://rspcourse.chinaedu.net/00700/499193_20180827_2/9E835990A7C24E72BD287AEBF4A1F152/res/3course!!%e8%a7%86%e9%a2%91%e8%ae%b2%e8%a7%a3/027%e4%b9%a6%e9%9d%a2%e8%a1%a8%e8%be%be/%e5%88%87%e7%89%87/027%e4%b9%a6%e9%9d%a2%e8%a1%a8%e8%be%be/video.m3u8"
    }
  ],
  "version": "2018-08-16 13:14:13"
}